{
    "@schema": "https://raw.githubusercontent.com/slicer/slicer/master/Modules/Loadable/Markups/Resources/Schema/markups-schema-v1.0.3.json#",
    "markups": [
        {
            "type": "Curve",
            "coordinateSystem": "LPS",
            "coordinateUnits": "mm",
            "locked": false,
            "fixedNumberOfControlPoints": false,
            "labelFormat": "%N-%d",
            "lastUsedControlPointNumber": 21,
            "controlPoints": [
                {
                    "id": "77",
                    "label": "ligule-1",
                    "description": "",
                    "associatedNodeID": "",
                    "position": [13.063806533813477, 11.049103736877442, 10.239142417907715],
                    "orientation": [-1.0, -0.0, -0.0, -0.0, -1.0, -0.0, 0.0, 0.0, 1.0],
                    "selected": true,
                    "locked": true,
                    "visibility": true,
                    "positionStatus": "defined"
                },
                {
                    "id": "2",
                    "label": "ligule-2ligule-3",
                    "description": "",
                    "associatedNodeID": "",
                    "position": [13.23996353149414, 10.875239372253418, 10.453485488891602],
                    "orientation": [-1.0, -0.0, -0.0, -0.0, -1.0, -0.0, 0.0, 0.0, 1.0],
                    "selected": true,
                    "locked": true,
                    "visibility": true,
                    "positionStatus": "defined"
                },
                {
                    "id": "3",
                    "label": "ligule-4",
                    "description": "",
                    "associatedNodeID": "",
                    "position": [13.557040214538575, 10.77236270904541, 10.50321102142334],
                    "orientation": [-1.0, -0.0, -0.0, -0.0, -1.0, -0.0, 0.0, 0.0, 1.0],
                    "selected": true,
                    "locked": true,
                    "visibility": true,
                    "positionStatus": "defined"
                },
                {
                    "id": "4",
                    "label": "ligule-5",
                    "description": "",
                    "associatedNodeID": "",
                    "position": [13.87077808380127, 10.660717010498047, 10.553410530090332],
                    "orientation": [-1.0, -0.0, -0.0, -0.0, -1.0, -0.0, 0.0, 0.0, 1.0],
                    "selected": true,
                    "locked": true,
                    "visibility": true,
                    "positionStatus": "defined"
                },
                {
                    "id": "5",
                    "label": "",
                    "description": "",
                    "associatedNodeID": "",
                    "position": [14.190116882324219, 10.577703475952149, 10.491493225097657],
                    "orientation": [-1.0, -0.0, -0.0, -0.0, -1.0, -0.0, 0.0, 0.0, 1.0],
                    "selected": true,
                    "locked": true,
                    "visibility": true,
                    "positionStatus": "defined"
                },
                {
                    "id": "6",
                    "label": "ligule-6",
                    "description": "",
                    "associatedNodeID": "",
                    "position": [14.46642780303955, 10.52149772644043, 10.313027381896973],
                    "orientation": [-1.0, -0.0, -0.0, -0.0, -1.0, -0.0, 0.0, 0.0, 1.0],
                    "selected": true,
                    "locked": true,
                    "visibility": true,
                    "positionStatus": "defined"
                },
                {
                    "id": "7",
                    "label": "ligule-7",
                    "description": "",
                    "associatedNodeID": "",
                    "position": [14.635032653808594, 10.50217056274414, 10.02354621887207],
                    "orientation": [-1.0, -0.0, -0.0, -0.0, -1.0, -0.0, 0.0, 0.0, 1.0],
                    "selected": true,
                    "locked": true,
                    "visibility": true,
                    "positionStatus": "defined"
                },
                {
                    "id": "8",
                    "label": "ligule-8",
                    "description": "",
                    "associatedNodeID": "",
                    "position": [14.72918701171875, 10.513340950012207, 9.70029067993164],
                    "orientation": [-1.0, -0.0, -0.0, -0.0, -1.0, -0.0, 0.0, 0.0, 1.0],
                    "selected": true,
                    "locked": true,
                    "visibility": true,
                    "positionStatus": "defined"
                },
                {
                    "id": "9",
                    "label": "ligule-9",
                    "description": "",
                    "associatedNodeID": "",
                    "position": [14.78148078918457, 10.550199508666993, 9.369297981262207],
                    "orientation": [-1.0, -0.0, -0.0, -0.0, -1.0, -0.0, 0.0, 0.0, 1.0],
                    "selected": true,
                    "locked": true,
                    "visibility": true,
                    "positionStatus": "defined"
                },
                {
                    "id": "10",
                    "label": "",
                    "description": "",
                    "associatedNodeID": "",
                    "position": [14.80787181854248, 10.609383583068848, 9.038280487060547],
                    "orientation": [-1.0, -0.0, -0.0, -0.0, -1.0, -0.0, 0.0, 0.0, 1.0],
                    "selected": true,
                    "locked": true,
                    "visibility": true,
                    "positionStatus": "defined"
                },
                {
                    "id": "11",
                    "label": "ligule-10",
                    "description": "",
                    "associatedNodeID": "",
                    "position": [14.835805892944336, 10.671381950378418, 8.707906723022461],
                    "orientation": [-1.0, -0.0, -0.0, -0.0, -1.0, -0.0, 0.0, 0.0, 1.0],
                    "selected": true,
                    "locked": true,
                    "visibility": true,
                    "positionStatus": "defined"
                },
                {
                    "id": "12",
                    "label": "",
                    "description": "",
                    "associatedNodeID": "",
                    "position": [14.917712211608887, 10.698715209960938, 8.384256362915039],
                    "orientation": [-1.0, -0.0, -0.0, -0.0, -1.0, -0.0, 0.0, 0.0, 1.0],
                    "selected": true,
                    "locked": true,
                    "visibility": true,
                    "positionStatus": "defined"
                },
                {
                    "id": "13",
                    "label": "ligule-11",
                    "description": "",
                    "associatedNodeID": "",
                    "position": [15.094099044799805, 10.59878158569336, 8.11840534210205],
                    "orientation": [-1.0, -0.0, -0.0, -0.0, -1.0, -0.0, 0.0, 0.0, 1.0],
                    "selected": true,
                    "locked": true,
                    "visibility": true,
                    "positionStatus": "defined"
                },
                {
                    "id": "14",
                    "label": "ligule-12",
                    "description": "",
                    "associatedNodeID": "",
                    "position": [15.241636276245118, 10.446374893188477, 7.856329917907715],
                    "orientation": [-1.0, -0.0, -0.0, -0.0, -1.0, -0.0, 0.0, 0.0, 1.0],
                    "selected": true,
                    "locked": true,
                    "visibility": true,
                    "positionStatus": "defined"
                },
                {
                    "id": "15",
                    "label": "",
                    "description": "",
                    "associatedNodeID": "",
                    "position": [15.369297981262207, 10.32302474975586, 7.569865703582764],
                    "orientation": [-1.0, -0.0, -0.0, -0.0, -1.0, -0.0, 0.0, 0.0, 1.0],
                    "selected": true,
                    "locked": true,
                    "visibility": true,
                    "positionStatus": "defined"
                },
                {
                    "id": "16",
                    "label": "ligule-13",
                    "description": "",
                    "associatedNodeID": "",
                    "position": [15.446904182434082, 10.261927604675293, 7.249897480010986],
                    "orientation": [-1.0, -0.0, -0.0, -0.0, -1.0, -0.0, 0.0, 0.0, 1.0],
                    "selected": true,
                    "locked": true,
                    "visibility": true,
                    "positionStatus": "defined"
                },
                {
                    "id": "17",
                    "label": "ligule-14",
                    "description": "",
                    "associatedNodeID": "",
                    "position": [15.450928688049317, 10.304938316345215, 6.916032314300537],
                    "orientation": [-1.0, -0.0, -0.0, -0.0, -1.0, -0.0, 0.0, 0.0, 1.0],
                    "selected": true,
                    "locked": true,
                    "visibility": true,
                    "positionStatus": "defined"
                },
                {
                    "id": "18",
                    "label": "ligule-15",
                    "description": "",
                    "associatedNodeID": "",
                    "position": [15.449764251708985, 10.379816055297852, 6.587387561798096],
                    "orientation": [-1.0, -0.0, -0.0, -0.0, -1.0, -0.0, 0.0, 0.0, 1.0],
                    "selected": true,
                    "locked": true,
                    "visibility": true,
                    "positionStatus": "defined"
                },
                {
                    "id": "19",
                    "label": "",
                    "description": "",
                    "associatedNodeID": "",
                    "position": [15.396727561950684, 10.475852012634278, 6.268698215484619],
                    "orientation": [-1.0, -0.0, -0.0, -0.0, -1.0, -0.0, 0.0, 0.0, 1.0],
                    "selected": true,
                    "locked": true,
                    "visibility": true,
                    "positionStatus": "defined"
                },
                {
                    "id": "20",
                    "label": "ligule-16ligule-17ligule-18ligule-19ligule-20",
                    "description": "",
                    "associatedNodeID": "",
                    "position": [15.315808296203614, 10.58018970489502, 5.958303451538086],
                    "orientation": [-1.0, -0.0, -0.0, -0.0, -1.0, -0.0, 0.0, 0.0, 1.0],
                    "selected": true,
                    "locked": true,
                    "visibility": true,
                    "positionStatus": "defined"
                }
            ],
            "measurements": [
                {
                    "name": "length",
                    "enabled": true,
                    "value": 6.406294468054785,
                    "units": "mm",
                    "printFormat": "%-#4.4gmm"
                },
                {
                    "name": "curvature mean",
                    "enabled": false,
                    "printFormat": "%5.3f %s"
                },
                {
                    "name": "curvature max",
                    "enabled": false,
                    "printFormat": "%5.3f %s"
                }
            ]
        }
    ]
}