{
    "@schema": "https://raw.githubusercontent.com/slicer/slicer/master/Modules/Loadable/Markups/Resources/Schema/markups-schema-v1.0.3.json#",
    "markups": [
        {
            "type": "Curve",
            "coordinateSystem": "LPS",
            "coordinateUnits": "mm",
            "locked": false,
            "fixedNumberOfControlPoints": false,
            "labelFormat": "%N-%d",
            "lastUsedControlPointNumber": 21,
            "controlPoints": [
                {
                    "id": "77",
                    "label": "ligule-1",
                    "description": "",
                    "associatedNodeID": "",
                    "position": [6.018808364868164, 9.27543830871582, 9.619138717651368],
                    "orientation": [-1.0, -0.0, -0.0, -0.0, -1.0, -0.0, 0.0, 0.0, 1.0],
                    "selected": true,
                    "locked": true,
                    "visibility": true,
                    "positionStatus": "defined"
                },
                {
                    "id": "2",
                    "label": "ligule-2",
                    "description": "",
                    "associatedNodeID": "",
                    "position": [5.890196323394775, 9.511391639709473, 9.735986709594727],
                    "orientation": [-1.0, -0.0, -0.0, -0.0, -1.0, -0.0, 0.0, 0.0, 1.0],
                    "selected": true,
                    "locked": true,
                    "visibility": true,
                    "positionStatus": "defined"
                },
                {
                    "id": "3",
                    "label": "",
                    "description": "",
                    "associatedNodeID": "",
                    "position": [5.752971649169922, 9.76474380493164, 9.755188941955567],
                    "orientation": [-1.0, -0.0, -0.0, -0.0, -1.0, -0.0, 0.0, 0.0, 1.0],
                    "selected": true,
                    "locked": true,
                    "visibility": true,
                    "positionStatus": "defined"
                },
                {
                    "id": "4",
                    "label": "ligule-3",
                    "description": "",
                    "associatedNodeID": "",
                    "position": [5.63936710357666, 10.009503364562989, 9.64136791229248],
                    "orientation": [-1.0, -0.0, -0.0, -0.0, -1.0, -0.0, 0.0, 0.0, 1.0],
                    "selected": true,
                    "locked": true,
                    "visibility": true,
                    "positionStatus": "defined"
                },
                {
                    "id": "5",
                    "label": "ligule-4",
                    "description": "",
                    "associatedNodeID": "",
                    "position": [5.562326431274414, 10.257533073425293, 9.506860733032227],
                    "orientation": [-1.0, -0.0, -0.0, -0.0, -1.0, -0.0, 0.0, 0.0, 1.0],
                    "selected": true,
                    "locked": true,
                    "visibility": true,
                    "positionStatus": "defined"
                },
                {
                    "id": "6",
                    "label": "ligule-5",
                    "description": "",
                    "associatedNodeID": "",
                    "position": [5.559701919555664, 10.438318252563477, 9.2815580368042],
                    "orientation": [-1.0, -0.0, -0.0, -0.0, -1.0, -0.0, 0.0, 0.0, 1.0],
                    "selected": true,
                    "locked": true,
                    "visibility": true,
                    "positionStatus": "defined"
                },
                {
                    "id": "7",
                    "label": "",
                    "description": "",
                    "associatedNodeID": "",
                    "position": [5.61956787109375, 10.52499771118164, 9.0087890625],
                    "orientation": [-1.0, -0.0, -0.0, -0.0, -1.0, -0.0, 0.0, 0.0, 1.0],
                    "selected": true,
                    "locked": true,
                    "visibility": true,
                    "positionStatus": "defined"
                },
                {
                    "id": "8",
                    "label": "ligule-6",
                    "description": "",
                    "associatedNodeID": "",
                    "position": [5.724730491638184, 10.556955337524414, 8.737663269042969],
                    "orientation": [-1.0, -0.0, -0.0, -0.0, -1.0, -0.0, 0.0, 0.0, 1.0],
                    "selected": true,
                    "locked": true,
                    "visibility": true,
                    "positionStatus": "defined"
                },
                {
                    "id": "9",
                    "label": "",
                    "description": "",
                    "associatedNodeID": "",
                    "position": [5.879814624786377, 10.536367416381836, 8.490371704101563],
                    "orientation": [-1.0, -0.0, -0.0, -0.0, -1.0, -0.0, 0.0, 0.0, 1.0],
                    "selected": true,
                    "locked": true,
                    "visibility": true,
                    "positionStatus": "defined"
                },
                {
                    "id": "10",
                    "label": "ligule-7",
                    "description": "",
                    "associatedNodeID": "",
                    "position": [6.063291072845459, 10.473642349243164, 8.270672798156739],
                    "orientation": [-1.0, -0.0, -0.0, -0.0, -1.0, -0.0, 0.0, 0.0, 1.0],
                    "selected": true,
                    "locked": true,
                    "visibility": true,
                    "positionStatus": "defined"
                },
                {
                    "id": "11",
                    "label": "ligule-8",
                    "description": "",
                    "associatedNodeID": "",
                    "position": [6.253162860870361, 10.39744758605957, 8.060790061950684],
                    "orientation": [-1.0, -0.0, -0.0, -0.0, -1.0, -0.0, 0.0, 0.0, 1.0],
                    "selected": true,
                    "locked": true,
                    "visibility": true,
                    "positionStatus": "defined"
                },
                {
                    "id": "12",
                    "label": "ligule-15ligule-16ligule-17ligule-18ligule-19ligule-20",
                    "description": "",
                    "associatedNodeID": "",
                    "position": [6.4050188064575199, 10.445866584777832, 7.822112083435059],
                    "orientation": [-1.0, -0.0, -0.0, -0.0, -1.0, -0.0, 0.0, 0.0, 1.0],
                    "selected": true,
                    "locked": true,
                    "visibility": true,
                    "positionStatus": "defined"
                },
                {
                    "id": "13",
                    "label": "ligule-9",
                    "description": "",
                    "associatedNodeID": "",
                    "position": [6.509973049163818, 10.599860191345215, 7.595849514007568],
                    "orientation": [-1.0, -0.0, -0.0, -0.0, -1.0, -0.0, 0.0, 0.0, 1.0],
                    "selected": true,
                    "locked": true,
                    "visibility": true,
                    "positionStatus": "defined"
                },
                {
                    "id": "14",
                    "label": "ligule-10",
                    "description": "",
                    "associatedNodeID": "",
                    "position": [6.634967803955078, 10.755224227905274, 7.380838394165039],
                    "orientation": [-1.0, -0.0, -0.0, -0.0, -1.0, -0.0, 0.0, 0.0, 1.0],
                    "selected": true,
                    "locked": true,
                    "visibility": true,
                    "positionStatus": "defined"
                },
                {
                    "id": "15",
                    "label": "",
                    "description": "",
                    "associatedNodeID": "",
                    "position": [6.768099784851074, 10.901394844055176, 7.164175510406494],
                    "orientation": [-1.0, -0.0, -0.0, -0.0, -1.0, -0.0, 0.0, 0.0, 1.0],
                    "selected": true,
                    "locked": true,
                    "visibility": true,
                    "positionStatus": "defined"
                },
                {
                    "id": "16",
                    "label": "ligule-11",
                    "description": "",
                    "associatedNodeID": "",
                    "position": [6.923532485961914, 11.01588249206543, 6.944405555725098],
                    "orientation": [-1.0, -0.0, -0.0, -0.0, -1.0, -0.0, 0.0, 0.0, 1.0],
                    "selected": true,
                    "locked": true,
                    "visibility": true,
                    "positionStatus": "defined"
                },
                {
                    "id": "17",
                    "label": "ligule-12",
                    "description": "",
                    "associatedNodeID": "",
                    "position": [7.104999542236328, 11.093070030212403, 6.727394104003906],
                    "orientation": [-1.0, -0.0, -0.0, -0.0, -1.0, -0.0, 0.0, 0.0, 1.0],
                    "selected": true,
                    "locked": true,
                    "visibility": true,
                    "positionStatus": "defined"
                },
                {
                    "id": "18",
                    "label": "",
                    "description": "",
                    "associatedNodeID": "",
                    "position": [7.268401622772217, 11.197266578674317, 6.507259368896484],
                    "orientation": [-1.0, -0.0, -0.0, -0.0, -1.0, -0.0, 0.0, 0.0, 1.0],
                    "selected": true,
                    "locked": true,
                    "visibility": true,
                    "positionStatus": "defined"
                },
                {
                    "id": "19",
                    "label": "ligule-13",
                    "description": "",
                    "associatedNodeID": "",
                    "position": [7.437589168548584, 11.307135581970215, 6.2943434715271],
                    "orientation": [-1.0, -0.0, -0.0, -0.0, -1.0, -0.0, 0.0, 0.0, 1.0],
                    "selected": true,
                    "locked": true,
                    "visibility": true,
                    "positionStatus": "defined"
                },
                {
                    "id": "20",
                    "label": "ligule-14",
                    "description": "",
                    "associatedNodeID": "",
                    "position": [7.615850925445557, 11.415072441101075, 6.087908744812012],
                    "orientation": [-1.0, -0.0, -0.0, -0.0, -1.0, -0.0, 0.0, 0.0, 1.0],
                    "selected": true,
                    "locked": true,
                    "visibility": true,
                    "positionStatus": "defined"
                }
            ],
            "measurements": [
                {
                    "name": "length",
                    "enabled": true,
                    "value": 5.570213049551725,
                    "units": "mm",
                    "printFormat": "%-#4.4gmm"
                },
                {
                    "name": "curvature mean",
                    "enabled": false,
                    "printFormat": "%5.3f %s"
                },
                {
                    "name": "curvature max",
                    "enabled": false,
                    "printFormat": "%5.3f %s"
                }
            ]
        }
    ]
}