{
    "@schema": "https://raw.githubusercontent.com/slicer/slicer/master/Modules/Loadable/Markups/Resources/Schema/markups-schema-v1.0.3.json#",
    "markups": [
        {
            "type": "Curve",
            "coordinateSystem": "LPS",
            "coordinateUnits": "mm",
            "locked": false,
            "fixedNumberOfControlPoints": false,
            "labelFormat": "%N-%d",
            "lastUsedControlPointNumber": 11,
            "controlPoints": [
                {
                    "id": "1",
                    "label": "fil_top-1fil_top-9fil_top-10",
                    "description": "",
                    "associatedNodeID": "",
                    "position": [9.015806198120118, 7.178347587585449, 9.807294845581055],
                    "orientation": [-1.0, -0.0, -0.0, -0.0, -1.0, -0.0, 0.0, 0.0, 1.0],
                    "selected": true,
                    "locked": true,
                    "visibility": true,
                    "positionStatus": "defined"
                },
                {
                    "id": "2",
                    "label": "fil_top-2",
                    "description": "",
                    "associatedNodeID": "",
                    "position": [9.069178581237793, 7.366785049438477, 9.881230354309082],
                    "orientation": [-1.0, -0.0, -0.0, -0.0, -1.0, -0.0, 0.0, 0.0, 1.0],
                    "selected": true,
                    "locked": true,
                    "visibility": true,
                    "positionStatus": "defined"
                },
                {
                    "id": "3",
                    "label": "fil_top-3",
                    "description": "",
                    "associatedNodeID": "",
                    "position": [9.152382850646973, 7.514796733856201, 10.011008262634278],
                    "orientation": [-1.0, -0.0, -0.0, -0.0, -1.0, -0.0, 0.0, 0.0, 1.0],
                    "selected": true,
                    "locked": true,
                    "visibility": true,
                    "positionStatus": "defined"
                },
                {
                    "id": "4",
                    "label": "",
                    "description": "",
                    "associatedNodeID": "",
                    "position": [9.223152160644532, 7.674925327301025, 10.13296127319336],
                    "orientation": [-1.0, -0.0, -0.0, -0.0, -1.0, -0.0, 0.0, 0.0, 1.0],
                    "selected": true,
                    "locked": true,
                    "visibility": true,
                    "positionStatus": "defined"
                },
                {
                    "id": "5",
                    "label": "fil_top-4",
                    "description": "",
                    "associatedNodeID": "",
                    "position": [9.26623821258545, 7.859055995941162, 10.232173919677735],
                    "orientation": [-1.0, -0.0, -0.0, -0.0, -1.0, -0.0, 0.0, 0.0, 1.0],
                    "selected": true,
                    "locked": true,
                    "visibility": true,
                    "positionStatus": "defined"
                },
                {
                    "id": "6",
                    "label": "fil_top-5",
                    "description": "",
                    "associatedNodeID": "",
                    "position": [9.294282913208008, 8.055525779724121, 10.311014175415039],
                    "orientation": [-1.0, -0.0, -0.0, -0.0, -1.0, -0.0, 0.0, 0.0, 1.0],
                    "selected": true,
                    "locked": true,
                    "visibility": true,
                    "positionStatus": "defined"
                },
                {
                    "id": "7",
                    "label": "fil_top-6",
                    "description": "",
                    "associatedNodeID": "",
                    "position": [9.312849998474121, 8.262482643127442, 10.360669136047364],
                    "orientation": [-1.0, -0.0, -0.0, -0.0, -1.0, -0.0, 0.0, 0.0, 1.0],
                    "selected": true,
                    "locked": true,
                    "visibility": true,
                    "positionStatus": "defined"
                },
                {
                    "id": "8",
                    "label": "",
                    "description": "",
                    "associatedNodeID": "",
                    "position": [9.308444023132325, 8.469714164733887, 10.412548065185547],
                    "orientation": [-1.0, -0.0, -0.0, -0.0, -1.0, -0.0, 0.0, 0.0, 1.0],
                    "selected": true,
                    "locked": true,
                    "visibility": true,
                    "positionStatus": "defined"
                },
                {
                    "id": "9",
                    "label": "fil_top-7",
                    "description": "",
                    "associatedNodeID": "",
                    "position": [9.285429000854493, 8.678068161010743, 10.453859329223633],
                    "orientation": [-1.0, -0.0, -0.0, -0.0, -1.0, -0.0, 0.0, 0.0, 1.0],
                    "selected": true,
                    "locked": true,
                    "visibility": true,
                    "positionStatus": "defined"
                },
                {
                    "id": "10",
                    "label": "fil_top-8",
                    "description": "",
                    "associatedNodeID": "",
                    "position": [9.251144409179688, 8.887314796447754, 10.480742454528809],
                    "orientation": [-1.0, -0.0, -0.0, -0.0, -1.0, -0.0, 0.0, 0.0, 1.0],
                    "selected": true,
                    "locked": true,
                    "visibility": true,
                    "positionStatus": "defined"
                }
            ],
            "measurements": [
                {
                    "name": "length",
                    "enabled": true,
                    "value": 1.9210329127447177,
                    "units": "mm",
                    "printFormat": "%-#4.4gmm"
                },
                {
                    "name": "curvature mean",
                    "enabled": true,
                    "value": 0.8195385423788714,
                    "units": "mm-1",
                    "printFormat": "%5.3f %s"
                },
                {
                    "name": "curvature max",
                    "enabled": true,
                    "value": 2.686275026575624,
                    "units": "mm-1",
                    "printFormat": "%5.3f %s"
                }
            ]
        }
    ]
}